basic_return/BasicReturn.py
basic_return/__init__.py
basic_return-0.1.0.11.dist-info/LICENSE
basic_return-0.1.0.11.dist-info/WHEEL
basic_return-0.1.0.11.dist-info/METADATA
basic_return-0.1.0.11.dist-info/RECORD
