Metadata-Version: 2.1
Name: basic-return
Version: 0.1.0.11
Summary: 
Home-page: https://github.com/henriquelino/basic_return
Author: henrique lino
Author-email: henrique.lino97@gmail.com
Requires-Python: >=3.9,<4.0
Classifier: Programming Language :: Python :: 3
Classifier: Programming Language :: Python :: 3.9
Classifier: Programming Language :: Python :: 3.10
Classifier: Programming Language :: Python :: 3.11
Project-URL: Repository, https://github.com/henriquelino/basic_return
